{
  "version": "5.9.0",
  "flags": {},
  "shapes": [
    {
      "label": "Lamp",
      "points": [
        [
          1030.1238390092906,
          411.36222910216657
        ],
        [
          1113.0185758513994,
          495.57275541795804
        ]
      ],
      "group_id": null,
      "description": "",
      "shape_type": "rectangle",
      "flags": {},
      "mask": null
    }
  ],
  "imagePath": "DJI_0067_t300.000s.jpg",
  "imageData": null,
  "imageHeight": 1080,
  "imageWidth": 1920
}