{
  "version": "5.9.0",
  "flags": {},
  "shapes": [
    {
      "label": "Lamp",
      "points": [
        [
          1122.2291021671842,
          309.38854489164
        ],
        [
          1205.12383900929,
          393.59907120743105
        ]
      ],
      "group_id": null,
      "description": "",
      "shape_type": "rectangle",
      "flags": {},
      "mask": null
    }
  ],
  "imagePath": "DJI_0444_t300.000s.jpg",
  "imageData": null,
  "imageHeight": 1080,
  "imageWidth": 1920
}